Workbook

Sheet 00 House Style
B2: NEK GROUP — DOCUMENT HOUSE STYLE
B3: The fixed standard for every finance document template.
B5: TYPOGRAPHY & NUMBERS
B6: Font | C6: Arial throughout.
B7: Currency label | C7: MYR as the label. 'Ringgit Malaysia' only in the amount-in-words line.
B8: Amount format | C8: Accounting, two decimals: #,##0.00.
B9: Date format | C9: YYYY-MM-DD everywhere.
B11: ENTITY & LETTERHEAD
B12: Driven by | C12: Entity Code. Letterhead looked up, never typed.
B13: Header shows | C13: Full legal name, Co. Reg. No., office address, Tel & Email.
B14: Contact line | C14: Tel: 012-4820853 Email: nekgroup84@gmail.com (no fax).
B15: Source of truth | C15: Master register. _EntityData / _BankAccounts here are an interim mirror until generation is automated.
B17: REFERENCE NUMBER SCHEME
B18: Format | C18: DOCTYPE / ENTITY / BANKCODE / YYYYMM / NNN
B19: Example | C19: PV/NEK/BOC/202607/014
B20: Bank code | C20: The account the money is paid from (PV) or into (OR, INV). Codes live in the Bank Account register.
B21: NNN | C21: Sequential per doc type per entity, reset to 001 each calendar year. YYYYMM records the month.
B22: Doc type codes | C22: PV = Payment Voucher · RV = Receiving Voucher · OR = Official Receipt · INV = Invoice · SAL = Salary Slip
C23: IMPORTANT — this reference (with slashes) is what prints on the document. A FILE name cannot contain '/', so when a document is saved the slashes become hyphens, e.g. reference PV/NEK/BOC/202607/014 -> file ...PV-NEK-BOC-202607-014.pdf, inside the YYYY-MM-DD_ENTITY_DOCTYPE_... convention. The automation handles this conversion.
B25: DOCUMENT FAMILIES
B26: Outward-facing | C26: Invoice (INV), Official Receipt (OR). Branded letterhead, no signatory block.
B27: Internal control | C27: Payment Voucher (PV), Receiving Voucher (RV). Prepared / Issued / Approved / Received block.
B28: Employee-facing | C28: Salary Slip (SAL). No signatory block.
B30: PAGE SETUP & FOOTER
B31: Paper | C31: A4 portrait, fit to 1 page wide, print area = document body only.
B32: Margins | C32: 0.5" sides, 0.6" top/bottom.
B33: Footer | C33: 'Computer-generated' line on outward + salary docs; signatory block on internal vouchers.
B35: FILLING A TEMPLATE
B36: Yellow cells | C36: Input. Everything else is a formula.
B37: Control panel | C37: Yellow panel to the right: Entity Code, Bank Code, Running No. Fill it and the letterhead + reference build themselves. It sits outside the print area. A warning shows if the bank code isn't linked to the entity.

Sheet _Currency
A1: CURRENCY WORDING - written from scripts/amount_in_words.py on every run. Do not hand-edit; the script is the source.
A2: Code | B2: Major Unit | C2: Minor Unit
A3: HKD | B3: Hong Kong Dollars | C3: Cents
A4: MYR | B4: Ringgit Malaysia | C4: Sen
A5: USD | B5: US Dollars | C5: Cents

Sheet _EntityData
A1: ENTITY LOOKUP — interim mirror of the Entity register.
A2: Entity Code | B2: Legal Name | C2: Co. Reg. No. | D2: Office Address | E2: Currency | F2: Tel | G2: Email
A3: NEK | B3: Ng Eng Kee & Sons Sdn Bhd | C3: 198401003022 (115540-H) | D3: 51-10-E, Menara BHL, Jalan Sultan Ahmad Shah, 10050 Georgetown, Penang, Malaysia | E3: MYR | F3: 012-4820853 | G3: nekgroup84@gmail.com
A4: NEKGV | B4: NEK Global Venture Sdn Bhd | C4: 201701005849 (1220014-K) | D4: 51-10-E, Menara BHL, Jalan Sultan Ahmad Shah, 10050 Georgetown, Penang, Malaysia | E4: MYR | F4: 012-4820853 | G4: nekgroup84@gmail.com
A5: MDL | B5: Marque De Luxe Sdn Bhd | C5: 201801034932 (1296959-W) | D5: 51-10-E, Menara BHL, Jalan Sultan Ahmad Shah, 10050 Georgetown, Penang, Malaysia | E5: MYR | F5: 012-4820853 | G5: nekgroup84@gmail.com
A6: HHIL | B6: Honour Harvest International Limited | C6: 202002000010 (995780-D) | D6: 51-10-E, Menara BHL, Jalan Sultan Ahmad Shah, 10050 Georgetown, Penang, Malaysia | E6: MYR | F6: 012-4820853 | G6: nekgroup84@gmail.com
A7: NGCS | B7: NGCS Capital Sdn Bhd | C7: 202201029491 (1475188-H) | D7: 51-10-E, Menara BHL, Jalan Sultan Ahmad Shah, 10050 Georgetown, Penang, Malaysia | E7: MYR | F7: 012-4820853 | G7: nekgroup84@gmail.com
A8: NCLCAP | B8: NCL Capital Sdn Bhd | C8: 202201030761 (1476458-K) | D8: 51-10-E, Menara BHL, Jalan Sultan Ahmad Shah, 10050 Georgetown, Penang, Malaysia | E8: MYR | F8: 012-4820853 | G8: nekgroup84@gmail.com
A9: SBOXCAP | B9: Sandbox Capital Sdn Bhd | C9: 202101001994 | D9: 51-10-E, Menara BHL, Jalan Sultan Ahmad Shah, 10050 Georgetown, Penang, Malaysia | E9: MYR | F9: 012-4820853 | G9: nekgroup84@gmail.com
A10: SBOXAI | B10: Sandbox AI Ventures Sdn Bhd | C10: 202301011872 (1505794-W) | D10: 51-10-E, Menara BHL, Jalan Sultan Ahmad Shah, 10050 Georgetown, Penang, Malaysia | E10: MYR | F10: 012-4820853 | G10: nekgroup84@gmail.com
A11: NCL | B11: Ng Chong Lam | D11: 33, Denai Bayu 2, Jalan Seri Tanjung Pinang, 10470 Tanjung Tokong, Penang, Malaysia | E11: HKD | F11: 012-4820853 | G11: nekgroup84@gmail.com
A12: CSK | B12: Chiang Sau Kuen | D12: 33, Denai Bayu 2, Jalan Seri Tanjung Pinang, 10470 Tanjung Tokong, Penang, Malaysia | E12: HKD | F12: 012-4820853 | G12: nekgroup84@gmail.com
A13: WT | B13: Wintrace Investment | E13: USD | F13: 012-4820853 | G13: nekgroup84@gmail.com

Sheet _BankAccounts
A1: BANK LOOKUP — interim mirror of the Bank Account register. Key = Entity|BankCode.
A2: Key | B2: Bank Code | C2: Entity Code | D2: Bank Name | E2: Currency | F2: Account Name | G2: Account No.
A3: NEK|BOC | B3: BOC | C3: NEK | D3: Bank of China (Malaysia) Berhad | E3: MYR | F3: [account name] | G3: [to confirm]
A4: NEK|MBB | B4: MBB | C4: NEK | D4: Malayan Banking Berhad (Maybank) | E4: MYR | F4: [account name] | G4: [to confirm]
A5: NEKGV|UOB | B5: UOB | C5: NEKGV | D5: United Overseas Bank (Malaysia) | E5: MYR | F5: [account name] | G5: [to confirm]
A6: MDL|UOB | B6: UOB | C6: MDL | D6: United Overseas Bank (Malaysia) | E6: MYR | F6: [account name] | G6: [to confirm]
A7: HHIL|BOC | B7: BOC | C7: HHIL | D7: Bank of China (Malaysia) Berhad | E7: MYR | F7: [account name] | G7: [to confirm]
A8: NGCS|OCBC | B8: OCBC | C8: NGCS | D8: OCBC Bank (Malaysia) Berhad | E8: MYR | F8: [account name] | G8: [to confirm]
A9: NCLCAP|BOC | B9: BOC | C9: NCLCAP | D9: Bank of China (Malaysia) Berhad | E9: MYR | F9: [account name] | G9: [to confirm]
A10: SBOXCAP|UOB | B10: UOB | C10: SBOXCAP | D10: United Overseas Bank (Malaysia) | E10: MYR | F10: [account name] | G10: [to confirm]
A11: SBOXAI|UOB | B11: UOB | C11: SBOXAI | D11: United Overseas Bank (Malaysia) | E11: MYR | F11: [account name] | G11: [to confirm]
A12: NCL|BOCOM | B12: BOCOM | C12: NCL | D12: Bank of Communications (Hong Kong) | E12: HKD | F12: [account name] | G12: [to confirm]
A13: WT|TBC | B13: TBC | C13: WT | D13: [to confirm] | E13: USD | F13: [account name] | G13: [to confirm]

Sheet Payment Voucher
A1: =IFERROR(INDEX(_EntityData!$B$3:$B$100,MATCH($K$3,_EntityData!$A$3:$A$100,0)),"") -> Ng Eng Kee & Sons Sdn Bhd | J1: CONTROL PANEL
A2: =IF($K$3="","",IFERROR(IF(INDEX(_EntityData!$C$3:$C$100,MATCH($K$3,_EntityData!$A$3:$A$100,0))="","","Co. Reg. No. "&INDEX(_EntityData!$C$3:$C$100,MATCH($K$3,_EntityData!$A$3:$A$100,0))),"")) -> Co. Reg. No. 198401003022 (115540-H) | J2: Fill yellow cells; document updates itself.
A3: =IF($K$3="","",IFERROR("Tel: "&INDEX(_EntityData!$F$3:$F$100,MATCH($K$3,_EntityData!$A$3:$A$100,0))&" Email: "&INDEX(_EntityData!$G$3:$G$100,MATCH($K$3,_EntityData!$A$3:$A$100,0)),"")) -> Tel: 012-4820853 Email: nekgroup84@gmail.com | J3: Entity Code | K3: NEK
A4: =IFERROR(INDEX(_EntityData!$D$3:$D$100,MATCH($K$3,_EntityData!$A$3:$A$100,0)),"") -> 51-10-E, Menara BHL, Jalan Sultan Ahmad Shah, 10050 Georgetown, Penang, Malaysia | J4: Bank Code | K4: BOC
A5: PAYMENT VOUCHER | J5: Running No. | K5: 14
J6: Bank (from code) | K6: =IFERROR(INDEX(_BankAccounts!$D$3:$D$100,MATCH($K$3&"|"&$K$4,_BankAccounts!$A$3:$A$100,0)),"") -> Bank of China (Malaysia) Berhad
A7: PAY TO : | B7: [name] | F7: PV NO : | G7: =K7 -> PV/NEK/BOC/202607/014 | J7: Reference (auto) | K7: =IF(OR($K$3="",$K$4="",$K$5="",G9=""),"","PV/"&$K$3&"/"&$K$4&"/"&TEXT(G9,"yyyymm")&"/"&TEXT($K$5,"000")) -> PV/NEK/BOC/202607/014
F8: Mode of Payment : | G8: IBG | J8: Check | K8: =IF(OR($K$3="",$K$4=""),"",IF(ISNUMBER(MATCH($K$3&"|"&$K$4,_BankAccounts!$A$3:$A$100,0)),"","! bank code not linked to this entity"))
F9: DATE : | G9: 46228 | J9: Currency (auto) | K9: =IFERROR(INDEX(_BankAccounts!$E$3:$E$100,MATCH($K$3&"|"&$K$4,_BankAccounts!$A$3:$A$100,0)),"") -> MYR
A11: IN PAYMENT FOR | E11: =$K$9 -> MYR | G11: ACCOUNTS CODE
A12: EPF Payable — Jul 2026 | E12: 2793
A18: TOTAL | E18: =SUM(E12:F17) -> 2793
A20: =IF($K$9="","",IFERROR(INDEX(_Currency!$B$3:$B$20,MATCH($K$9,_Currency!$A$3:$A$20,0)),$K$9)&" :") -> Ringgit Malaysia :
A23: ISSUED BY | E23: Signature :
A25: CHECKED BY | E25: Signature :
A27: APPROVED BY | E27: Signature :

Sheet Receiving Voucher
A1: =IFERROR(INDEX(_EntityData!$B$3:$B$100,MATCH($K$3,_EntityData!$A$3:$A$100,0)),"") -> Ng Eng Kee & Sons Sdn Bhd | J1: CONTROL PANEL
A2: =IF($K$3="","",IFERROR(IF(INDEX(_EntityData!$C$3:$C$100,MATCH($K$3,_EntityData!$A$3:$A$100,0))="","","Co. Reg. No. "&INDEX(_EntityData!$C$3:$C$100,MATCH($K$3,_EntityData!$A$3:$A$100,0))),"")) -> Co. Reg. No. 198401003022 (115540-H) | J2: Fill yellow cells; document updates itself.
A3: =IF($K$3="","",IFERROR("Tel: "&INDEX(_EntityData!$F$3:$F$100,MATCH($K$3,_EntityData!$A$3:$A$100,0))&" Email: "&INDEX(_EntityData!$G$3:$G$100,MATCH($K$3,_EntityData!$A$3:$A$100,0)),"")) -> Tel: 012-4820853 Email: nekgroup84@gmail.com | J3: Entity Code | K3: NEK
A4: =IFERROR(INDEX(_EntityData!$D$3:$D$100,MATCH($K$3,_EntityData!$A$3:$A$100,0)),"") -> 51-10-E, Menara BHL, Jalan Sultan Ahmad Shah, 10050 Georgetown, Penang, Malaysia | J4: Bank Code | K4: BOC
A5: RECEIVING VOUCHER | J5: Running No. | K5: 14
J6: Bank (from code) | K6: =IFERROR(INDEX(_BankAccounts!$D$3:$D$100,MATCH($K$3&"|"&$K$4,_BankAccounts!$A$3:$A$100,0)),"") -> Bank of China (Malaysia) Berhad
A7: RECEIVED FM : | B7: [name] | F7: RV NO : | G7: =K7 -> RV/NEK/BOC/202607/014 | J7: Reference (auto) | K7: =IF(OR($K$3="",$K$4="",$K$5="",G9=""),"","RV/"&$K$3&"/"&$K$4&"/"&TEXT(G9,"yyyymm")&"/"&TEXT($K$5,"000")) -> RV/NEK/BOC/202607/014
F8: Mode of Payment : | G8: IBG | J8: Check | K8: =IF(OR($K$3="",$K$4=""),"",IF(ISNUMBER(MATCH($K$3&"|"&$K$4,_BankAccounts!$A$3:$A$100,0)),"","! bank code not linked to this entity"))
F9: DATE : | G9: 46228 | J9: Currency (auto) | K9: =IFERROR(INDEX(_BankAccounts!$E$3:$E$100,MATCH($K$3&"|"&$K$4,_BankAccounts!$A$3:$A$100,0)),"") -> MYR
A11: IN PAYMENT FOR | E11: =$K$9 -> MYR | G11: ACCOUNTS CODE
A12: EPF Payable — Jul 2026 | E12: 2793
A18: TOTAL | E18: =SUM(E12:F17) -> 2793
A20: =IF($K$9="","",IFERROR(INDEX(_Currency!$B$3:$B$20,MATCH($K$9,_Currency!$A$3:$A$20,0)),$K$9)&" :") -> Ringgit Malaysia :
A23: ISSUED BY | E23: Signature :
A25: CHECKED BY | E25: Signature :
A27: APPROVED BY | E27: Signature :

Sheet Invoice
A1: =IFERROR(INDEX(_EntityData!$B$3:$B$100,MATCH($K$3,_EntityData!$A$3:$A$100,0)),"") -> Ng Eng Kee & Sons Sdn Bhd | J1: CONTROL PANEL
A2: =IF($K$3="","",IFERROR(IF(INDEX(_EntityData!$C$3:$C$100,MATCH($K$3,_EntityData!$A$3:$A$100,0))="","","Co. Reg. No. "&INDEX(_EntityData!$C$3:$C$100,MATCH($K$3,_EntityData!$A$3:$A$100,0))),"")) -> Co. Reg. No. 198401003022 (115540-H) | J2: Fill yellow cells; document updates itself.
A3: =IF($K$3="","",IFERROR("Tel: "&INDEX(_EntityData!$F$3:$F$100,MATCH($K$3,_EntityData!$A$3:$A$100,0))&" Email: "&INDEX(_EntityData!$G$3:$G$100,MATCH($K$3,_EntityData!$A$3:$A$100,0)),"")) -> Tel: 012-4820853 Email: nekgroup84@gmail.com | J3: Entity Code | K3: NEK
A4: =IFERROR(INDEX(_EntityData!$D$3:$D$100,MATCH($K$3,_EntityData!$A$3:$A$100,0)),"") -> 51-10-E, Menara BHL, Jalan Sultan Ahmad Shah, 10050 Georgetown, Penang, Malaysia | J4: Bank Code | K4: MBB
A5: INVOICE | J5: Running No. | K5: 14
J6: Bank (from code) | K6: =IFERROR(INDEX(_BankAccounts!$D$3:$D$100,MATCH($K$3&"|"&$K$4,_BankAccounts!$A$3:$A$100,0)),"") -> Malayan Banking Berhad (Maybank)
A7: Billed To : | G7: Invoice No. : | H7: =K7 -> INV/NEK/MBB/202607/014 | J7: Reference (auto) | K7: =IF(OR($K$3="",$K$4="",$K$5="",H8=""),"","INV/"&$K$3&"/"&$K$4&"/"&TEXT(H8,"yyyymm")&"/"&TEXT($K$5,"000")) -> INV/NEK/MBB/202607/014
A8: [name] | G8: DATE : | H8: 46204 | J8: Check | K8: =IF(OR($K$3="",$K$4=""),"",IF(ISNUMBER(MATCH($K$3&"|"&$K$4,_BankAccounts!$A$3:$A$100,0)),"","! bank code not linked to this entity"))
A9: [unit / address — from Property or Vendor register] | J9: Currency (auto) | K9: =IFERROR(INDEX(_BankAccounts!$E$3:$E$100,MATCH($K$3&"|"&$K$4,_BankAccounts!$A$3:$A$100,0)),"") -> MYR
A11: ITEM | C11: DESCRIPTION | G11: =IF($K$9="","AMOUNT","AMOUNT ("&$K$9&")") -> AMOUNT (MYR)
A12: 1 | C12: RENTAL (July 2026) — 1G-10-03, Andaman Quayside | G12: 9000
A18: Total Amount | G18: =SUM(G12:H17) -> 9000
A20: =IF($K$9="","",IFERROR(INDEX(_Currency!$B$3:$B$20,MATCH($K$9,_Currency!$A$3:$A$20,0)),$K$9)&" :") -> Ringgit Malaysia : | B20: [amount in words]
A22: All payments should be crossed and made payable to the company named above.
A23: =IF($K$3="","","Bank : "&IFERROR(INDEX(_BankAccounts!$D$3:$D$100,MATCH($K$3&"|"&$K$4,_BankAccounts!$A$3:$A$100,0)),"")) -> Bank : Malayan Banking Berhad (Maybank)
A25: This is a computer-generated document. No signature is required.

Sheet Official Receipt
A1: =IFERROR(INDEX(_EntityData!$B$3:$B$100,MATCH($K$3,_EntityData!$A$3:$A$100,0)),"") -> Ng Eng Kee & Sons Sdn Bhd | J1: CONTROL PANEL
A2: =IF($K$3="","",IFERROR(IF(INDEX(_EntityData!$C$3:$C$100,MATCH($K$3,_EntityData!$A$3:$A$100,0))="","","Co. Reg. No. "&INDEX(_EntityData!$C$3:$C$100,MATCH($K$3,_EntityData!$A$3:$A$100,0))),"")) -> Co. Reg. No. 198401003022 (115540-H) | J2: Fill yellow cells; document updates itself.
A3: =IF($K$3="","",IFERROR("Tel: "&INDEX(_EntityData!$F$3:$F$100,MATCH($K$3,_EntityData!$A$3:$A$100,0))&" Email: "&INDEX(_EntityData!$G$3:$G$100,MATCH($K$3,_EntityData!$A$3:$A$100,0)),"")) -> Tel: 012-4820853 Email: nekgroup84@gmail.com | J3: Entity Code | K3: NEK
A4: =IFERROR(INDEX(_EntityData!$D$3:$D$100,MATCH($K$3,_EntityData!$A$3:$A$100,0)),"") -> 51-10-E, Menara BHL, Jalan Sultan Ahmad Shah, 10050 Georgetown, Penang, Malaysia | J4: Bank Code | K4: BOC
A5: OFFICIAL RECEIPT | J5: Running No. | K5: 14
J6: Bank (from code) | K6: =IFERROR(INDEX(_BankAccounts!$D$3:$D$100,MATCH($K$3&"|"&$K$4,_BankAccounts!$A$3:$A$100,0)),"") -> Bank of China (Malaysia) Berhad
A7: Received From : | G7: Receipt No. : | H7: =K7 -> OR/NEK/BOC/202607/014 | J7: Reference (auto) | K7: =IF(OR($K$3="",$K$4="",$K$5="",H8=""),"","OR/"&$K$3&"/"&$K$4&"/"&TEXT(H8,"yyyymm")&"/"&TEXT($K$5,"000")) -> OR/NEK/BOC/202607/014
A8: [name] | G8: DATE : | H8: 46204 | J8: Check | K8: =IF(OR($K$3="",$K$4=""),"",IF(ISNUMBER(MATCH($K$3&"|"&$K$4,_BankAccounts!$A$3:$A$100,0)),"","! bank code not linked to this entity"))
A9: [unit / address — from Property or Vendor register] | J9: Currency (auto) | K9: =IFERROR(INDEX(_BankAccounts!$E$3:$E$100,MATCH($K$3&"|"&$K$4,_BankAccounts!$A$3:$A$100,0)),"") -> MYR
A11: ITEM | C11: DESCRIPTION | G11: =IF($K$9="","AMOUNT","AMOUNT ("&$K$9&")") -> AMOUNT (MYR)
A12: 1 | C12: RENTAL (July 2026) — 1G-10-03, Andaman Quayside | G12: 9000
A18: Total Amount | G18: =SUM(G12:H17) -> 9000
A20: =IF($K$9="","",IFERROR(INDEX(_Currency!$B$3:$B$20,MATCH($K$9,_Currency!$A$3:$A$20,0)),$K$9)&" :") -> Ringgit Malaysia : | B20: [amount in words]
A22: Payment Mode : | C22: Bank Transfer
A23: Bank : | C23: =IFERROR(INDEX(_BankAccounts!$D$3:$D$100,MATCH($K$3&"|"&$K$4,_BankAccounts!$A$3:$A$100,0)),"") -> Bank of China (Malaysia) Berhad
A24: Transaction Ref : | C24: [txn no.]
A26: This official receipt is valid only upon clearance of the transaction.
A28: This is a computer-generated document. No signature is required.

Sheet Salary Slip
A1: =IFERROR(INDEX(_EntityData!$B$3:$B$100,MATCH($K$3,_EntityData!$A$3:$A$100,0)),"") -> Ng Eng Kee & Sons Sdn Bhd | J1: CONTROL PANEL
A2: =IF($K$3="","",IFERROR(IF(INDEX(_EntityData!$C$3:$C$100,MATCH($K$3,_EntityData!$A$3:$A$100,0))="","","Co. Reg. No. "&INDEX(_EntityData!$C$3:$C$100,MATCH($K$3,_EntityData!$A$3:$A$100,0))),"")) -> Co. Reg. No. 198401003022 (115540-H) | J2: Fill yellow cells; document updates itself.
A3: =IF($K$3="","",IFERROR("Tel: "&INDEX(_EntityData!$F$3:$F$100,MATCH($K$3,_EntityData!$A$3:$A$100,0))&" Email: "&INDEX(_EntityData!$G$3:$G$100,MATCH($K$3,_EntityData!$A$3:$A$100,0)),"")) -> Tel: 012-4820853 Email: nekgroup84@gmail.com | J3: Entity Code | K3: NEK
A4: =IFERROR(INDEX(_EntityData!$D$3:$D$100,MATCH($K$3,_EntityData!$A$3:$A$100,0)),"") -> 51-10-E, Menara BHL, Jalan Sultan Ahmad Shah, 10050 Georgetown, Penang, Malaysia | J4: Bank Code | K4: BOC
A5: MONTHLY SALARY SLIP | J5: Running No. | K5: 14
J6: Bank (from code) | K6: =IFERROR(INDEX(_BankAccounts!$D$3:$D$100,MATCH($K$3&"|"&$K$4,_BankAccounts!$A$3:$A$100,0)),"") -> Bank of China (Malaysia) Berhad
A7: Payroll Month : | B7: July 2026 | E7: Employee Code : | F7: [code] | J7: Reference (auto) | K7: =IF(OR($K$3="",$K$4="",$K$5="",$K$9=""),"","SAL/"&$K$3&"/"&$K$4&"/"&TEXT($K$9,"yyyymm")&"/"&TEXT($K$5,"000")) -> SAL/NEK/BOC/202607/014
A8: Employee Name : | B8: [employee name] | E8: Payment Currency : | F8: MYR | J8: Check | K8: =IF(OR($K$3="",$K$4=""),"",IF(ISNUMBER(MATCH($K$3&"|"&$K$4,_BankAccounts!$A$3:$A$100,0)),"","! bank code not linked to this entity"))
E9: Payslip Ref : | F9: =K7 -> SAL/NEK/BOC/202607/014 | J9: Payroll Date | K9: 46228
A10: EARNINGS | E10: EMPLOYER CONTRIBUTIONS
A11: Basic Pay | B11: MYR | C11: 6500 | E11: Employer's EPF | F11: MYR | G11: 816
A12: Allowance | B12: MYR | C12: 300 | E12: Employer's SOCSO | F12: MYR | G12: 104.15
E13: Employer's EIS | F13: MYR | G13: 11.9
A14: Gross Pay | B14: MYR | C14: =C11+C12 -> 6800 | E14: Total Employer Contribution | F14: MYR | G14: =SUM(G11:G13) -> 932.05
A16: DEDUCTIONS
A17: EPF - Employee | B17: MYR | C17: 748
A18: SOCSO - Employee | B18: MYR | C18: 29.75
A19: EIS - Employee | B19: MYR | C19: 11.9
A20: SOCSO 24-Hour (NEIS) | B20: MYR | C20: 44.65
A21: PCB / Income Tax | B21: MYR | C21: 295.5
A22: Total Deductions | B22: MYR | C22: =SUM(C17:C21) -> 1129.8
A24: PAY SUMMARY
A25: Gross Pay | B25: MYR | C25: =C14 -> 6800
A26: Less: Total Deductions | B26: MYR | C26: =C22 -> 1129.8
A27: NET PAY | B27: MYR | C27: =C25-C26 -> 5670.2
A29: This is a computer-generated payslip. No signature is required. For payroll record purposes only.
